arguments/__init__.py
arguments/__init__.pyi
class_arguments-0.0.2.dist-info/METADATA
class_arguments-0.0.2.dist-info/WHEEL
class_arguments-0.0.2.dist-info/top_level.txt
class_arguments-0.0.2.dist-info/RECORD
