Metadata-Version: 2.1
Name: class-arguments
Version: 0.0.2
Summary: UNKNOWN
Home-page: https://github.com/yulinfeng000/class_arguments
Author: cam
Author-email: yulinfeng000@gmail.com
License: UNKNOWN
Platform: UNKNOWN
Classifier: Programming Language :: Python :: 3
Classifier: License :: OSI Approved :: MIT License
